paramspace2d/__init__.py
paramspace2d/paramspace.py
parameter_space_2d-0.1.4.dist-info/LICENSE
parameter_space_2d-0.1.4.dist-info/METADATA
parameter_space_2d-0.1.4.dist-info/WHEEL
parameter_space_2d-0.1.4.dist-info/top_level.txt
parameter_space_2d-0.1.4.dist-info/RECORD
