Metadata-Version: 2.1
Name: parameter-space-2d
Version: 0.1.4
Summary: Tools for performing 2D parameter space analysis for deterministic models
Author: Tom Bland
Author-email: tom_bland@hotmail.co.uk
License: CC BY 4.0
Project-URL: Source Code, https://github.com/tsmbland/parameter-space-2d
License-File: LICENSE
Requires-Dist: numpy
Requires-Dist: matplotlib
